{
  "cards": [
    {
      "id": "BQ-ARC-0001",
      "name": "Crystal Shard",
      "type": "Action",
      "faction": "Arcane",
      "rarity": "Common",
      "cost": { "energy": 2 },
      "text": "Deal 2 damage to target. If it dies, gain 1 Energy.",
      "rules": { "damage": 2, "onKill": {"energy": 1} },
      "icons": ["crystal", "damage"],
      "flavor": "The crystal's power flows through you.",
      "v": 2
    },
    {
      "id": "BQ-ARC-0002",
      "name": "Crystal Resonance",
      "type": "Program",
      "faction": "Arcane",
      "rarity": "Rare",
      "cost": { "energy": 4 },
      "text": "Duration: 3 rounds. All spells have +1 range and deal +1 damage.",
      "rules": { "duration": 3, "spellBuff": {"range": 1, "damage": 1} },
      "icons": ["program", "crystal"],
      "flavor": "The crystal sings with power.",
      "v": 2
    },
    {
      "id": "BQ-ARC-0003",
      "name": "Crystal Focus",
      "type": "Structure",
      "faction": "Arcane",
      "rarity": "Rare",
      "cost": { "energy": 4, "bricks": 6 },
      "buildReq": { 
        "bricks": { "regular": 4, "plates": 1, "special": 1, "total": 6 },
        "lego": ["crystal:1", "focus_lens:1"], 
        "stl": ["crystal_focus"], 
        "footprint": "1-hex" 
      },
      "text": "All spells cost −1 Energy. When you cast a spell, deal 1 damage to a random enemy. Cost: 6 bricks (4 regular, 1 plate, 1 special).",
      "rules": { "spellDiscount": 1, "onSpellCast": {"damage": 1, "target": "randomEnemy"} },
      "icons": ["crystal", "focus"],
      "flavor": "The crystal amplifies all magic.",
      "v": 2
    },
    {
      "id": "BQ-ARC-0004",
      "name": "Crystal Shard",
      "type": "Consumable",
      "faction": "Arcane",
      "rarity": "Rare",
      "cost": { "energy": 2 },
      "text": "Deal 3 damage to target. If it dies, gain 2 Energy and draw 1 card.",
      "rules": { "damage": 3, "onKill": {"energy": 2, "draw": 1} },
      "icons": ["crystal", "shard"],
      "flavor": "The crystal's final gift.",
      "v": 2
    },
    {
      "id": "BQ-ARC-0005",
      "name": "Storm Spire",
      "type": "Structure",
      "faction": "Arcane",
      "rarity": "Mythic",
      "cost": { "energy": 5 },
      "buildReq": { "lego": ["crystal:2", "storm_rod:1"], "stl": ["storm_spire"], "footprint": "1-hex" },
      "text": "At round start, deal 1 damage to all enemies. All Weather cards last +1 round.",
      "rules": { "roundStart": {"damage": 1, "target": "enemies"}, "weatherBuff": {"duration": 1} },
      "icons": ["storm", "crystal"],
      "flavor": "The storm answers to none.",
      "v": 2
    },
    {
      "id": "BQ-ARC-0006",
      "name": "Rune Trap",
      "type": "Trap",
      "faction": "Arcane",
      "rarity": "Uncommon",
      "cost": { "energy": 2 },
      "text": "Arm on any tile. When enemy enters: they are Stunned for 1 round and take 2 damage.",
      "rules": { "arm": true, "trigger": "onEnterTile", "statusAdd": [{"name": "Stunned", "dur": 1}], "damage": 2 },
      "icons": ["trap", "rune"],
      "flavor": "The ancient runes hold power.",
      "v": 2
    },
    {
      "id": "BQ-ARC-0007",
      "name": "Voltaic Storm",
      "type": "Weather",
      "faction": "Arcane",
      "rarity": "Uncommon",
      "cost": { "energy": 2 },
      "text": "Lasts 3 rounds. At round end, each unit in exposed tiles takes 1 damage (⚡). Sensors gain +1 range.",
      "rules": { "durationRounds": 3, "endRoundTick": { "aoeDamage": 1, "tag": "electric" }, "buffs": {"sensorRange": 1} },
      "icons": ["storm", "sensor"],
      "flavor": "The storm rages on.",
      "v": 2
    },
    {
      "id": "BQ-ARC-0008",
      "name": "Reality Rift",
      "type": "Event",
      "faction": "Arcane",
      "rarity": "Rare",
      "cost": { "energy": 3 },
      "text": "All units are teleported to random tiles. Draw 2 cards.",
      "rules": { "teleport": "random", "target": "all", "draw": 2 },
      "icons": ["event", "rift"],
      "flavor": "The fabric of reality tears.",
      "v": 2
    },
    {
      "id": "BQ-ARC-0009",
      "name": "Crystal Wall",
      "type": "Structure",
      "faction": "Arcane",
      "rarity": "Common",
      "cost": { "energy": 2, "bricks": 4 },
      "buildReq": { 
        "bricks": { "regular": 4, "plates": 0, "special": 0, "total": 4 },
        "lego": ["crystal:2"], 
        "stl": ["crystal_wall"], 
        "footprint": "1-hex" 
      },
      "text": "Provides cover (+2 Defense) to adjacent units. Cost: 4 bricks (4 regular).",
      "rules": { "cover": 2, "adjacent": true },
      "icons": ["crystal", "wall", "defense"],
      "flavor": "A shimmering barrier of pure crystal.",
      "v": 2
    },
    {
      "id": "BQ-ARC-0010",
      "name": "Mystic Turret",
      "type": "Structure",
      "faction": "Arcane",
      "rarity": "Uncommon",
      "cost": { "energy": 3, "bricks": 8 },
      "buildReq": { 
        "bricks": { "regular": 6, "plates": 1, "special": 1, "total": 8 },
        "lego": ["crystal:1", "focus_lens:1", "turret_base:1"], 
        "stl": ["mystic_turret"], 
        "footprint": "1-hex" 
      },
      "text": "Ranged attack: 3 damage, 3 range. Can target flying units. Cost: 8 bricks (6 regular, 1 plate, 1 special).",
      "rules": { "attack": 3, "range": 3, "flying": true },
      "icons": ["crystal", "turret", "ranged"],
      "flavor": "The turret channels arcane energy into devastating blasts.",
      "v": 2
    },
    {
      "id": "BQ-ARC-0011",
      "name": "Portal Gateway",
      "type": "Structure",
      "faction": "Arcane",
      "rarity": "Rare",
      "cost": { "energy": 5, "bricks": 12 },
      "buildReq": { 
        "bricks": { "regular": 8, "plates": 2, "special": 2, "total": 12 },
        "lego": ["crystal:3", "portal_frame:1", "energy_core:1"], 
        "stl": ["portal_gateway"], 
        "footprint": "2-hex" 
      },
      "text": "Allies can teleport to any other Portal Gateway. Cost: 12 bricks (8 regular, 2 plates, 2 special).",
      "rules": { "teleport": "portal", "allies": true },
      "icons": ["crystal", "portal", "teleport"],
      "flavor": "A gateway between distant points in space.",
      "v": 2
    }
  ],
  "metadata": {
    "faction": "Arcane",
    "totalCards": 11,
    "version": "1.0.0"
  }
}
